cashflex/__init__.py
cashflex/__main__.py
cashflex/desktop/cashflex.desktop
cashflex/icons/128x128/uk.co.contrelec.cashflex.svg
cashflex/icons/16x16/uk.co.contrelec.cashflex.svg
cashflex/icons/256x256/uk.co.contrelec.cashflex.svg
cashflex/icons/32x32/uk.co.contrelec.cashflex.svg
cashflex/icons/64x64/uk.co.contrelec.cashflex.svg
cashflex/images/add_income.svg
cashflex/images/add_income_component.svg
cashflex/images/add_payment.svg
cashflex/images/add_pocket.svg
cashflex/images/forecast_1.svg
cashflex/images/forecast_2.svg
cashflex/images/forecast_page.svg
cashflex/images/income_component_complete.svg
cashflex/images/new_pocket.svg
cashflex/images/payment_component.svg
cashflex/images/payment_components.svg
cashflex/images/pocket_current_account.svg
cashflex/images/pocket_savings_account.svg
cashflex/scripts/install.sh
cashflex/src/__init__.py
cashflex/src/custom.py
cashflex/src/db.py
cashflex/src/forecast.py
cashflex/src/menu.py
cashflex/src/pockets.py
cashflex/src/utils.py
cashflex/src/window.py
cashflex/src/css/cashflex.css
cashflex/src/db/cashflex.db
cashflex/src/ui/alert.ui
cashflex/src/ui/alert_cancel_ok.ui
cashflex/src/ui/calendar.ui
cashflex/src/ui/delete.ui
cashflex/src/ui/menu.ui
cashflex/src/ui/window.ui
cashflex-1.0.24.dist-info/METADATA
cashflex-1.0.24.dist-info/WHEEL
cashflex-1.0.24.dist-info/top_level.txt
cashflex-1.0.24.dist-info/RECORD
