Metadata-Version: 2.1
Name: cashflex
Version: 1.0.24
Summary: Cashflex Money Manager
Author: Gary Barnes
Author-email: gary.barnes2023@gmail.com
Project-URL: Documentation, https://github.com/gary-1959/cashflex/blob/main/README.md
Project-URL: Source, https://github.com/gary-1959/cashflex
Project-URL: Tracker, https://github.com/gary-1959/cashflex/issues
Classifier: Development Status :: 4 - Beta
Classifier: Intended Audience :: End Users/Desktop
Classifier: License :: Free for non-commercial use
Classifier: Natural Language :: English
Classifier: Programming Language :: Python :: 3
Classifier: Topic :: Office/Business :: Financial :: Accounting
Requires-Python: >=3.10
Requires-Dist: matplotlib >=3.8
